<?xml version="1.0" encoding="UTF-8"?>
<metadata xml:lang="en"><Esri><CreaDate>20160317</CreaDate><CreaTime>13280700</CreaTime><ArcGISFormat>1.0</ArcGISFormat><SyncOnce>TRUE</SyncOnce><DataProperties><itemProps><itemLocation><linkage Sync="TRUE">file://\\DESKTOP-Q8POHA4\C\Users\emhun\Desktop\MSFF_Docs\Files\SpatialData\HMDA_MI_2004</linkage><protocol Sync="TRUE">Local Area Network</protocol></itemLocation></itemProps><copyHistory><copy source="H:\HMDAPlay\HMDA_MI_2004" dest="\\DESKTOP-Q8POHA4\C\Users\emhun\Desktop\MSFF_Docs\Files\SpatialData\HMDA_MI_2004" date="20160317" time="13280700"></copy></copyHistory></DataProperties></Esri></metadata>
